mwispy/__init__.py
mwispy/converter.py
mwispy/cubemoment.py
mwispy/datacube.py
mwispy/easyplotlib.py
mwispy/mosaic.py
mwispy/pvslice.py
mwispy/tile.py
mwispy-1.0.6.dist-info/LICENSE
mwispy-1.0.6.dist-info/METADATA
mwispy-1.0.6.dist-info/WHEEL
mwispy-1.0.6.dist-info/top_level.txt
mwispy-1.0.6.dist-info/RECORD
