Metadata-Version: 2.1
Name: mwispy
Version: 1.0.6
Summary: Tools for MWISP data reduction.
Author-email: Shaobo Zhang <shbzhang@pmo.ac.cn>
Project-URL: Homepage, https://github.com/shbzhang/mwispy
Classifier: Programming Language :: Python :: 3
Classifier: License :: OSI Approved :: MIT License
Classifier: Operating System :: OS Independent
Requires-Python: >=3.7
License-File: LICENSE
Requires-Dist: numpy >=1.21.0
Requires-Dist: scipy >=1.7.0
Requires-Dist: matplotlib >=3.4.0
Requires-Dist: astropy >=4.3
Requires-Dist: spectral-cube >=0.6.2
Requires-Dist: tqdm >=4.62.0
